README.md
setup.py
neonUtilities/NeonAOP.py
neonUtilities/NeonInstrumental.py
neonUtilities/NeonObservational.py
neonUtilities/__init__.py
neonUtilities/neon.py
py_neonUtilities.egg-info/PKG-INFO
py_neonUtilities.egg-info/SOURCES.txt
py_neonUtilities.egg-info/dependency_links.txt
py_neonUtilities.egg-info/top_level.txt