Metadata-Version: 2.1
Name: py-neonUtilities
Version: 0.5.4
Summary: A native python wrapper for the NEON ecological database api
Home-page: https://gitlab.com/esrh/py-neonutils
Author: esrh
Author-email: esrh@netc.eu
License: UNKNOWN
Keywords: NEON data ecology api
Platform: UNKNOWN
Requires-Python: >=3.6
